{
  "api": "https://ccpanel-rdoiv8ae63cbnz2.netmonitoring.ir",
  "shield": "https://cpanel-2cdhxscoaq7fyrm.netmonitoring.ir",
  "download": "https://cpanel-po5uuj792hoi626.netmonitoring.ir",
  "websocket": "cpanel-wsapi-5xonyxm7ch5dret.netmonitoring.ir",
  "alternative_api": "https://ccpanel-rdoiv8ae63cbnz2.netmonitoring.ir",
  "alternative_shield": "https://cpanel-2cdhxscoaq7fyrm.netmonitoring.ir",
  "alternative_download": "https://cpanel-po5uuj792hoi626.netmonitoring.ir",
  "alternative_websocket": "cpanel-wsapi-5xonyxm7ch5dret.netmonitoring.ir",
  "vip_purchase": "https://t.me/QuickPingBot?start=buy",
  "android_download": {
    "google_play": "https://play.google.com/store/apps/details?id=org.quickping",
    "telegram": "https://t.me/QuickPing/130",
    "website": "https://quickping.app/app/quick.apk"
  },
  "ios_download": {
    "app_store": "https://apps.apple.com/us/app/"
  },
  "windows_download": {
    "telegram": "https://t.me/QuickPing/130",
    "website": "https://quickping.app/app/quick.exe"
  },
  "remote_shield_urls_enabled": true,
  "shield_urls": {
    "malware": [
      "https://quickserver.storage.c2.liara.space/geosite-malware.srs",
      "https://quickserver.storage.c2.liara.space/geoip-malware.srs",
      "https://quickserver.storage.c2.liara.space/malware.srs",
      "https://quickserver.storage.c2.liara.space/geosite-cryptominers.srs",
      "https://quickserver.storage.c2.liara.space/cryptominers.srs"
    ],
    "ads_trackers": [
      "https://quickserver.storage.c2.liara.space/geosite-category-ads-all.srs",
      "https://quickserver.storage.c2.liara.space/category-ads-all.srs",
      "https://quickserver.storage.c2.liara.space/category-public-tracker.srs",
      "https://quickserver.storage.c2.liara.space/tracker.srs"
    ],
    "phishing": [
      "https://quickserver.storage.c2.liara.space/geosite-phishing.srs",
      "https://quickserver.storage.c2.liara.space/geoip-phishing.srs",
      "https://quickserver.storage.c2.liara.space/phishing.srs"
    ],
    "porn": [
      "https://quickserver.storage.c2.liara.space/category-porn.srs",
      "https://quickserver.storage.c2.liara.space/Porn.srs"
    ],
    "gov": [
      "https://quickserver.storage.c2.liara.space/category-gov-ir.srs",
      "https://quickserver.storage.c2.liara.space/category-gov-ru.srs"
    ],
    "social": [
      "https://quickserver.storage.c2.liara.space/category-social-media-!cn.srs",
      "https://quickserver.storage.c2.liara.space/category-social-media-cn.srs",
      "https://quickserver.storage.c2.liara.space/category-social-media-ir.srs"
    ],
    "crypto": [
      "https://quickserver.storage.c2.liara.space/category-cryptocurrency.srs",
      "https://quickserver.storage.c2.liara.space/Crypto.srs"
    ],
    "ir": [
      "https://quickserver.storage.c2.liara.space/geosite-ir.srs",
      "https://quickserver.storage.c2.liara.space/geoip-ir.srs"
    ]
  }
}
